example/__init__.py
example/cfg/__init__.py
example/cfg/cfg_live.py
example/cfg/cfg_manual.py
example/cfg/cfg_rf_live.py
example/cfg/parameters.py
example/cfg/reconstruction.py
gui4us/__init__.py
gui4us/__main__.py
gui4us/common.py
gui4us/controller.py
gui4us/logging.py
gui4us/model.py
gui4us/settings.py
gui4us/state_graph.py
gui4us/utils.py
gui4us/version.py
gui4us/view.py
gui4us/cfg/__init__.py
gui4us/cfg/display.py
gui4us/cfg/environment.py
gui4us/controller/__init__.py
gui4us/controller/app.py
gui4us/controller/buffer.py
gui4us/controller/env.py
gui4us/controller/event.py
gui4us/controller/task.py
gui4us/model/__init__.py
gui4us/model/app.py
gui4us/model/core.py
gui4us/model/envs/__init__.py
gui4us/model/envs/arrus.py
gui4us/view/__init__.py
gui4us/view/capture_buffer.py
gui4us/view/common.py
gui4us/view/control.py
gui4us/view/env.py
gui4us/view/settings.py
gui4us/view/view.py
gui4us/view/widgets.py
gui4us/view/display/__init__.py
gui4us/view/display/main_panel.py
gui4us/view/display/impl/__init__.py
gui4us/view/display/impl/matplotlib/__init__.py
gui4us/view/display/impl/vtk/__init__.py
gui4us-0.3.0.dev20250318.dist-info/LICENSE
gui4us-0.3.0.dev20250318.dist-info/METADATA
gui4us-0.3.0.dev20250318.dist-info/WHEEL
gui4us-0.3.0.dev20250318.dist-info/entry_points.txt
gui4us-0.3.0.dev20250318.dist-info/top_level.txt
gui4us-0.3.0.dev20250318.dist-info/RECORD
