Metadata-Version: 2.1
Name: gui4us
Version: 0.3.0.dev20250318
Summary: GUI 4 ultrasound
Home-page: https://us4us.eu
Author: us4us Ltd.
Author-email: support@us4us.eu
License: UNKNOWN
Platform: UNKNOWN
Classifier: Development Status :: 1 - Planning
Classifier: Intended Audience :: Developers
Classifier: Intended Audience :: Science/Research
Classifier: Programming Language :: Python :: 3
Classifier: Operating System :: OS Independent
Classifier: Topic :: Software Development :: Embedded Systems
Classifier: Topic :: Scientific/Engineering :: Bio-Informatics
Classifier: Topic :: Scientific/Engineering :: Medical Science Apps.
Requires-Python: >=3.8
License-File: LICENSE
Requires-Dist: arrus (>=0.10.0)
Requires-Dist: pyyaml (==6.0)
Requires-Dist: PyQt5 (==5.15.9)
Requires-Dist: PyQt5-Qt5 (==5.15.2)
Requires-Dist: PyQt5-sip (==12.12.1)
Requires-Dist: matplotlib (==3.7.2)
